AUTHORS
LICENSE
MANIFEST.in
README.rst
setup.py
django_smarter.egg-info/PKG-INFO
django_smarter.egg-info/SOURCES.txt
django_smarter.egg-info/dependency_links.txt
django_smarter.egg-info/top_level.txt
smarter/__init__.py
smarter/models.py
smarter/tests.py
smarter/templates/smarter/_ajax.html
smarter/templates/smarter/_form.html
smarter/templates/smarter/add.html
smarter/templates/smarter/details.html
smarter/templates/smarter/edit.html
smarter/templates/smarter/index.html
smarter/templates/smarter/remove.html