Metadata-Version: 1.1
Name: django-smarter
Version: 1.1
Summary: Smarter declarative style generic views for Django.
Home-page: https://github.com/05bit/django-smarter
Author: Alexey Kinyov
Author-email: rudy@05bit.com
License: BSD
Keywords: django,application,scaffolding,crud,views,utility
Platform: UNKNOWN
Classifier: Development Status :: 4 - Beta
Classifier: Operating System :: OS Independent
Classifier: License :: OSI Approved :: BSD License
Classifier: Intended Audience :: Developers
Classifier: Environment :: Web Environment
Classifier: Programming Language :: Python :: 2.5
Classifier: Programming Language :: Python :: 2.6
Classifier: Programming Language :: Python :: 2.7
